allooptim/__init__.py
allooptim/allocation_to_allocators/__init__.py
allooptim/allocation_to_allocators/a2a_config.py
allooptim/allocation_to_allocators/a2a_orchestrator.py
allooptim/allocation_to_allocators/a2a_result.py
allooptim/allocation_to_allocators/allocation_optimizer.py
allooptim/allocation_to_allocators/data_provider_factory.py
allooptim/allocation_to_allocators/equal_weight_orchestrator.py
allooptim/allocation_to_allocators/error_estimator.py
allooptim/allocation_to_allocators/observation_simulator.py
allooptim/allocation_to_allocators/optimized_orchestrator.py
allooptim/allocation_to_allocators/optimizer_convergence.py
allooptim/allocation_to_allocators/optimizer_simulator.py
allooptim/allocation_to_allocators/orchestrator_factory.py
allooptim/allocation_to_allocators/simulator_interface.py
allooptim/allocation_to_allocators/wikipedia_pipeline_orchestrator.py
allooptim/backtest/__init__.py
allooptim/backtest/backtest_config.py
allooptim/backtest/backtest_engine.py
allooptim/backtest/backtest_quantstats.py
allooptim/backtest/backtest_report.py
allooptim/backtest/backtest_visualizer.py
allooptim/backtest/cluster_analyzer.py
allooptim/backtest/data_cleaning.py
allooptim/backtest/data_loader.py
allooptim/backtest/performance_metrics.py
allooptim/config/__init__.py
allooptim/config/allocation_dataclasses.py
allooptim/config/default_pydantic_config.py
allooptim/config/stock_dataclasses.py
allooptim/config/stock_universe.py
allooptim/covariance_transformer/__init__.py
allooptim/covariance_transformer/covariance_autoencoder.py
allooptim/covariance_transformer/covariance_transformer.py
allooptim/covariance_transformer/transformer_interface.py
allooptim/covariance_transformer/transformer_list.py
allooptim/data_generation/__init__.py
allooptim/data_generation/diverse_covariance_generator.py
allooptim/data_generation/diverse_training_data.py
allooptim/data_generation/generate_30k_dataset.py
allooptim/data_generation/generate_5k_dataset.py
allooptim-0.3.2.dist-info/METADATA
allooptim-0.3.2.dist-info/WHEEL
allooptim-0.3.2.dist-info/licenses/LICENSE
allooptim-0.3.2.dist-info/RECORD
