Metadata-Version: 2.4
Name: allooptim
Version: 0.3.2
Summary: Scientific portfolio optimization for institutional investors
License: MIT
License-File: LICENSE
Keywords: portfolio,optimization,finance,asset-allocation,quantitative-finance
Author: Jonas ten Haaf
Author-email: jonas.tenhaaf@mail.de
Requires-Python: >=3.11.0,<4.0.0
Classifier: Development Status :: 4 - Beta
Classifier: Intended Audience :: Financial and Insurance Industry
Classifier: Intended Audience :: Science/Research
Classifier: License :: OSI Approved :: MIT License
Classifier: Programming Language :: Python :: 3
Classifier: Programming Language :: Python :: 3.11
Classifier: Programming Language :: Python :: 3.12
Classifier: Programming Language :: Python :: 3.13
Classifier: Programming Language :: Python :: 3.14
Classifier: Topic :: Office/Business :: Financial :: Investment
Classifier: Topic :: Scientific/Engineering :: Mathematics
Requires-Dist: cma (>=4.4.0,<5.0.0)
Requires-Dist: h5py (>=3.15.1,<4.0.0)
Requires-Dist: lightgbm (>=4.6.0,<5.0.0)
Requires-Dist: lmo (>=0.14.2,<0.15.0)
Requires-Dist: numpy (>=2.3.4,<3.0.0)
Requires-Dist: pageviewapi (>=0.4.0,<0.5.0)
Requires-Dist: pandas (>=2.3.3,<3.0.0)
Requires-Dist: pydantic (>=2.12.3,<3.0.0)
Requires-Dist: pyportfolioopt (>=1.5.6,<2.0.0)
Requires-Dist: pyswarms (>=1.3.0,<2.0.0)
Requires-Dist: scikit-learn (>=1.7.2,<2.0.0)
Requires-Dist: scipy (>=1.16.1,<2.0.0)
Requires-Dist: tinygrad (>=0.11.0,<0.12.0)
Requires-Dist: yfinance (>=0.2.66,<0.3.0)
Project-URL: Documentation, https://allooptim.readthedocs.io
Project-URL: Homepage, https://github.com/AlloOptim/allooptim-core
Project-URL: Repository, https://github.com/AlloOptim/allooptim-core
